{
  "model": {
    "type": "select",
    "property": "custom_model_data",
    "fallback": {
      "type": "model",
      "model": "item/iron_nugget"
    },
    "cases": [
      {
        "when": "s_stone",
        "model": {
          "type": "model",
          "model": "item/s_stone"
     	 }
      },
      {
        "when": "astral_ingot",
        "model": {
          "type": "model",
          "model": "item/astral_ingot"
        }
      },
            {
        "when": "astral_ore",
        "model": { "type": "model", "model": "item/astral_ore" }
      },
      {
        "when": "banlite_ingot",
        "model": { "type": "model", "model": "item/banlite_ingot" }
      },
      {
        "when": "banlite_ore",
        "model": { "type": "model", "model": "item/banlite_ore" }
      },
      {
        "when": "bloodcheater",
        "model": { "type": "model", "model": "item/bloodcheater" }
      },
      {
        "when": "bloodmagicbook",
        "model": { "type": "model", "model": "item/bloodmagicbook" }
      },
      {
        "when": "cosmilite_ingot",
        "model": { "type": "model", "model": "item/cosmilite_ingot" }
      },
      {
        "when": "darkmagicbook",
        "model": { "type": "model", "model": "item/darkmagicbook" }
      },
      {
        "when": "dreamsap",
        "model": { "type": "model", "model": "item/dreamsap" }
      },
      {
        "when": "earthmagicbook",
        "model": { "type": "model", "model": "item/earthmagicbook" }
      },
      {
        "when": "excalibur",
        "model": { "type": "model", "model": "item/excalibur" }
      },
      {
        "when": "galaxis_ingot",
        "model": { "type": "model", "model": "item/galaxis_ingot" }
      },
      {
        "when": "magicscroll",
        "model": { "type": "model", "model": "item/magicscroll" }
      },
      {
        "when": "metanova_ingot",
        "model": { "type": "model", "model": "item/metanova_ingot" }
      },
      {
        "when": "overdream_ingot",
        "model": { "type": "model", "model": "item/overdream_ingot" }
      },
      {
        "when": "pan",
        "model": { "type": "model", "model": "item/pan" }
      },
      {
        "when": "photoghast",
        "model": { "type": "model", "model": "item/photoghast" }
      },
      {
        "when": "soulmagicbook",
        "model": { "type": "model", "model": "item/soulmagicbook" }
      },
      {
        "when": "stardust",
        "model": { "type": "model", "model": "item/stardust" }
      },
      {
        "when": "stardustpotion",
        "model": { "type": "model", "model": "item/stardustpotion" }
      },
      {
        "when": "verdent_ingot",
        "model": { "type": "model", "model": "item/verdent_ingot" }
      },
      {
        "when": "voidchain_ingot",
        "model": { "type": "model", "model": "item/voidchain_ingot" }
      },
      {
        "when": "voidchain_ore",
        "model": { "type": "model", "model": "item/voidchain_ore" }
      },
      {
        "when": "voidmagicbook",
        "model": { "type": "model", "model": "item/voidmagicbook" }
      },
      {
        "when": "watermagicbook",
        "model": { "type": "model", "model": "item/watermagicbook" }
      },
      {
        "when": "woodmagicbook",
        "model": { "type": "model", "model": "item/woodmagicbook" }
      },
      {
        "when": "stardise",
        "model": { "type": "model", "model": "item/stardise" }
      },
      {
        "when": "angel_treads",
        "model": { "type": "model", "model": "item/angel_treads" }
      },
      {
        "when": "ark_of_the_cosmos",
        "model": { "type": "model", "model": "item/ark_of_the_cosmos" }
      },
      {
        "when": "ark_of_the_elements",
        "model": { "type": "model", "model": "item/ark_of_the_elements" }
      },
      {
        "when": "asgardian_aegis",
        "model": { "type": "model", "model": "item/asgardian_aegis" }
      },
      {
        "when": "ashes_of_calamity",
        "model": { "type": "model", "model": "item/ashes_of_calamity" }
      },
      {
        "when": "ataraxia",
        "model": { "type": "model", "model": "item/ataraxia" }
      },
      {
        "when": "chaos_stone",
        "model": { "type": "model", "model": "item/chaos_stone" }
      },
      {
        "when": "daawnlight_spirit_origin",
        "model": { "type": "model", "model": "item/daawnlight_spirit_origin" }
      },
      {
        "when": "dark_sun_ring",
        "model": { "type": "model", "model": "item/dark_sun_ring" }
      },
      {
        "when": "eldritch_soul_artifact",
        "model": { "type": "model", "model": "item/eldritch_soul_artifact" }
      },
      {
        "when": "eternity",
        "model": { "type": "model", "model": "item/eternity" }
      },
      {
        "when": "galactica_singularity",
        "model": { "type": "model", "model": "item/galactica_singularity" }
      },
      {
        "when": "galaxia",
        "model": { "type": "model", "model": "item/galaxia" }
      },
      {
        "when": "heart_of_darkness",
        "model": { "type": "model", "model": "item/heart_of_darkness" }
      },
      {
        "when": "majestic_guard",
        "model": { "type": "model", "model": "item/majestic_guard" }
      },
      {
        "when": "mana_polarizer",
        "model": { "type": "model", "model": "item/mana_polarizer" }
      },
      {
        "when": "nucleogenesis",
        "model": { "type": "model", "model": "item/nucleogenesis" }
      },
      {
        "when": "orderbringer",
        "model": { "type": "model", "model": "item/orderbringer" }
      },
      {
        "when": "reality_rupture",
        "model": { "type": "model", "model": "item/reality_rupture" }
      },
      {
        "when": "scarlet_devil",
        "model": { "type": "model", "model": "item/scarlet_devil" }
      },
      {
        "when": "seraph_tracers",
        "model": { "type": "model", "model": "item/seraph_tracers" }
      },
      {
        "when": "shadow_potion",
        "model": { "type": "model", "model": "item/shadow_potion" }
      },
      {
        "when": "shattered_community",
        "model": { "type": "model", "model": "item/shattered_community" }
      },
      {
        "when": "subsuming_vortex",
        "model": { "type": "model", "model": "item/subsuming_vortex" }
      },
      {
        "when": "wrathwing",
        "model": { "type": "model", "model": "item/wrathwing" }
      },
      {
        "when": "aerialite_bar",
        "model": { "type": "model", "model": "item/aerialite_bar" }
      },
      {
        "when": "aerialite_ore",
        "model": { "type": "model", "model": "item/aerialite_ore" }
      },
      {
        "when": "ashes_of_annihilation",
        "model": { "type": "model", "model": "item/ashes_of_annihilation" }
      },
      {
        "when": "astral_bar",
        "model": { "type": "model", "model": "item/astral_bar" }
      },
      {
        "when": "raw_astral_ore",
        "model": { "type": "model", "model": "item/raw_astral_ore" }
      },
      {
        "when": "auric_bar",
        "model": { "type": "model", "model": "item/auric_bar" }
      },
      {
        "when": "auric_ore",
        "model": { "type": "model", "model": "item/auric_ore" }
      },
      {
        "when": "biofusi_blade",
        "model": { "type": "model", "model": "item/biofusi_blade" }
      },
      {
        "when": "bloodstone_core",
        "model": { "type": "model", "model": "item/bloodstone_core" }
      },
      {
        "when": "comet_shard",
        "model": { "type": "model", "model": "item/comet_shard" }
      },
      {
        "when": "core_of_calamity",
        "model": { "type": "model", "model": "item/core_of_calamity" }
      },
      {
        "when": "cryonic_bar",
        "model": { "type": "model", "model": "item/cryonic_bar" }
      },
      {
        "when": "cryonic_ore",
        "model": { "type": "model", "model": "item/cryonic_ore" }
      },
      {
        "when": "dark_spark",
        "model": { "type": "model", "model": "item/dark_spark" }
      },
      {
        "when": "divine_geode",
        "model": { "type": "model", "model": "item/divine_geode" }
      },
      {
        "when": "energy_core",
        "model": { "type": "model", "model": "item/energy_core" }
      },
      {
        "when": "essence_of_elegum",
        "model": { "type": "model", "model": "item/essence_of_elegum" }
      },
      {
        "when": "essence_of_havoc",
        "model": { "type": "model", "model": "item/essence_of_havoc" }
      },
      {
        "when": "essence_of_sunlight",
        "model": { "type": "model", "model": "item/essence_of_sunlight" }
      },
      {
        "when": "ethereal_core",
        "model": { "type": "model", "model": "item/ethereal_core" }
      },
      {
        "when": "event_horizon",
        "model": { "type": "model", "model": "item/event_horizon" }
      },
      {
        "when": "exo_prism",
        "model": { "type": "model", "model": "item/exo_prism" }
      },
      {
        "when": "haunted_scroll",
        "model": { "type": "model", "model": "item/haunted_scroll" }
      },
      {
        "when": "life_alloy",
        "model": { "type": "model", "model": "item/life_alloy" }
      },
      {
        "when": "living_shard",
        "model": { "type": "model", "model": "item/living_shard" }
      },
      {
        "when": "miracle_matter",
        "model": { "type": "model", "model": "item/miracle_matter" }
      },
      {
        "when": "mysterious_circuitry",
        "model": { "type": "model", "model": "item/mysterious_circuitry" }
      },
      {
        "when": "necroplasm",
        "model": { "type": "model", "model": "item/necroplasm" }
      },
      {
        "when": "nuclear_fury",
        "model": { "type": "model", "model": "item/nuclear_fury" }
      },
      {
        "when": "omega_healing_potion",
        "model": { "type": "model", "model": "item/omega_healing_potion" }
      },
      {
        "when": "pearl_shard",
        "model": { "type": "model", "model": "item/pearl_shard" }
      },
      {
        "when": "perennial_bar",
        "model": { "type": "model", "model": "item/perennial_bar" }
      },
      {
        "when": "perennial_ore",
        "model": { "type": "model", "model": "item/perennial_ore" }
      },
      {
        "when": "phantom_heart",
        "model": { "type": "model", "model": "item/phantom_heart" }
      },
      {
        "when": "rancor",
        "model": { "type": "model", "model": "item/rancor" }
      },
      {
        "when": "recitation_of_the_beast",
        "model": { "type": "model", "model": "item/recitation_of_the_beast" }
      },
      {
        "when": "rouge_slash",
        "model": { "type": "model", "model": "item/rouge_slash" }
      },
      {
        "when": "scoria_bar",
        "model": { "type": "model", "model": "item/scoria_bar" }
      },
      {
        "when": "scoria_ore",
        "model": { "type": "model", "model": "item/scoria_ore" }
      },
      {
        "when": "shadowspec_bar",
        "model": { "type": "model", "model": "item/shadowspec_bar" }
      },
      {
        "when": "supreme_healing_potion",
        "model": { "type": "model", "model": "item/supreme_healing_potion" }
      },
      {
        "when": "supreme_mana_potion",
        "model": { "type": "model", "model": "item/supreme_mana_potion" }
      },
      {
        "when": "suspicious_scrap",
        "model": { "type": "model", "model": "item/suspicious_scrap" }
      },
      {
        "when": "uelibloom_bar",
        "model": { "type": "model", "model": "item/uelibloom_bar" }
      },
      {
        "when": "unholy_core",
        "model": { "type": "model", "model": "item/unholy_core" }
      },
      {
        "when": "yharon_soul_fragment",
        "model": { "type": "model", "model": "item/yharon_soul_fragment" }
      },
      {
        "when": "baguette",
        "model": { "type": "model", "model": "item/baguette" }
      },
      {
        "when": "blasphemous_donut",
        "model": { "type": "model", "model": "item/blasphemous_donut" }
      },
      {
        "when": "bleach_ball",
        "model": { "type": "model", "model": "item/bleach_ball" }
      },
      {
        "when": "blood_orange",
        "model": { "type": "model", "model": "item/blood_orange" }
      },
      {
        "when": "bloom_stone",
        "model": { "type": "model", "model": "item/bloom_stone" }
      },
      {
        "when": "blunder_booster",
        "model": { "type": "model", "model": "item/blunder_booster" }
      },
      {
        "when": "crimson_flask",
        "model": { "type": "model", "model": "item/crimson_flask" }
      },
      {
        "when": "dark_plasma",
        "model": { "type": "model", "model": "item/dark_plasma" }
      },
      {
        "when": "dragonfruit",
        "model": { "type": "model", "model": "item/dragonfruit" }
      },
      {
        "when": "elderberry",
        "model": { "type": "model", "model": "item/elderberry" }
      },
      {
        "when": "elemental_gauntlet",
        "model": { "type": "model", "model": "item/elemental_gauntlet" }
      },
      {
        "when": "grand_gelatin",
        "model": { "type": "model", "model": "item/grand_gelatin" }
      },
      {
        "when": "luxor_gift",
        "model": { "type": "model", "model": "item/luxor_gift" }
      },
      {
        "when": "miracle_fruit",
        "model": { "type": "model", "model": "item/miracle_fruit" }
      },
      {
        "when": "phantomic_artifact",
        "model": { "type": "model", "model": "item/phantomic_artifact" }
      },
      {
        "when": "radiance",
        "model": { "type": "model", "model": "item/radiance" }
      },
      {
        "when": "radiant_ooze",
        "model": { "type": "model", "model": "item/radiant_ooze" }
      },
      {
        "when": "statis_curse",
        "model": { "type": "model", "model": "item/statis_curse" }
      },
      {
        "when": "unstable_granite_core",
        "model": { "type": "model", "model": "item/unstable_granite_core" }
      },
      {
        "when": "vampiric_talisman",
        "model": { "type": "model", "model": "item/vampiric_talisman" }
      },
      {
        "when": "void_of_calamity",
        "model": { "type": "model", "model": "item/void_of_calamity" }
      },
      {
        "when": "void_of_extinction",
        "model": { "type": "model", "model": "item/void_of_extinction" }
      },
      {
        "when": "yharim_gift",
        "model": { "type": "model", "model": "item/yharim_gift" }
      },
       {
        "when": "dreamtastic",
        "model": { "type": "model", "model": "item/dreamtastic" }
      },
       {
        "when": "exorcism",
        "model": { "type": "model", "model": "item/exorcism" }
      },
      {
        "when": "radiant_crystal",
        "model": { "type": "model", "model": "item/radiant_crystal" }
      },
      {
        "when": "sealer",
        "model": { "type": "model", "model": "item/sealer" }
      },
      {
        "when": "cosmilite_bar",
        "model": { "type": "model", "model": "item/cosmilite_bar" }
      },
       {
        "when": "loreabyss",
        "model": { "type": "model", "model": "item/loreabyss" }
      },
      {
        "when": "loreaquaticscourge",
        "model": { "type": "model", "model": "item/loreaquaticscourge" }
      },
      {
        "when": "lorearchmage",
        "model": { "type": "model", "model": "item/lorearchmage" }
      },
      {
        "when": "loreastralinfection",
        "model": { "type": "model", "model": "item/loreastralinfection" }
      },
      {
        "when": "loreastrumaureus",
        "model": { "type": "model", "model": "item/loreastrumaureus" }
      },
      {
        "when": "loreastrumdeus",
        "model": { "type": "model", "model": "item/loreastrumdeus" }
      },
      {
        "when": "loreavatar",
        "model": { "type": "model", "model": "item/loreavatar" }
      },
      {
        "when": "loreawakening",
        "model": { "type": "model", "model": "item/loreawakening" }
      },
      {
        "when": "loreazafure",
        "model": { "type": "model", "model": "item/loreazafure" }
      },
      {
        "when": "lorebloodmoon",
        "model": { "type": "model", "model": "item/lorebloodmoon" }
      },
      {
        "when": "lorebrainofcthulhu",
        "model": { "type": "model", "model": "item/lorebrainofcthulhu" }
      },
      {
        "when": "lorebrimstoneelemental",
        "model": { "type": "model", "model": "item/lorebrimstoneelemental" }
      },
      {
        "when": "lorecalamitas",
        "model": { "type": "model", "model": "item/lorecalamitas" }
      },
      {
        "when": "lorecalamitasclone",
        "model": { "type": "model", "model": "item/lorecalamitasclone" }
      },
      {
        "when": "loreceaselessvoid",
        "model": { "type": "model", "model": "item/loreceaselessvoid" }
      },
      {
        "when": "lorecorruption",
        "model": { "type": "model", "model": "item/lorecorruption" }
      },
      {
        "when": "lorecrabulon",
        "model": { "type": "model", "model": "item/lorecrabulon" }
      },
      {
        "when": "lorecrimson",
        "model": { "type": "model", "model": "item/lorecrimson" }
      },
      {
        "when": "lorecynosure",
        "model": { "type": "model", "model": "item/lorecynosure" }
      },
      {
        "when": "loredesertscourge",
        "model": { "type": "model", "model": "item/loredesertscourge" }
      },
      {
        "when": "loredestroyer",
        "model": { "type": "model", "model": "item/loredestroyer" }
      },
      {
        "when": "loredevourerofgods",
        "model": { "type": "model", "model": "item/loredevourerofgods" }
      },
      {
        "when": "loredragonfolly",
        "model": { "type": "model", "model": "item/loredragonfolly" }
      },
      {
        "when": "loredukefishron",
        "model": { "type": "model", "model": "item/loredukefishron" }
      },
      {
        "when": "loreeaterofworlds",
        "model": { "type": "model", "model": "item/loreeaterofworlds" }
      },
      {
        "when": "loreempressoflight",
        "model": { "type": "model", "model": "item/loreempressoflight" }
      },
      {
        "when": "loreexomechs",
        "model": { "type": "model", "model": "item/loreexomechs" }
      },
      {
        "when": "loreeyeofcthulhu",
        "model": { "type": "model", "model": "item/loreeyeofcthulhu" }
      },
      {
        "when": "loregolem",
        "model": { "type": "model", "model": "item/loregolem" }
      },
      {
        "when": "lorehivemind",
        "model": { "type": "model", "model": "item/lorehivemind" }
      },
      {
        "when": "lorekingslime",
        "model": { "type": "model", "model": "item/lorekingslime" }
      },
      {
        "when": "loreleviathananahita",
        "model": { "type": "model", "model": "item/loreleviathananahita" }
      },
      {
        "when": "loremechs",
        "model": { "type": "model", "model": "item/loremechs" }
      },
      {
        "when": "lorenamelessdeity",
        "model": { "type": "model", "model": "item/lorenamelessdeity" }
      },
      {
        "when": "loreoldduke",
        "model": { "type": "model", "model": "item/loreoldduke" }
      },
      {
        "when": "loreperforators",
        "model": { "type": "model", "model": "item/loreperforators" }
      },
      {
        "when": "loreplaguebringergoliath",
        "model": { "type": "model", "model": "item/loreplaguebringergoliath" }
      },
      {
        "when": "loreplantera",
        "model": { "type": "model", "model": "item/loreplantera" }
      },
      {
        "when": "lorepolterghast",
        "model": { "type": "model", "model": "item/lorepolterghast" }
      },
      {
        "when": "loreprelude",
        "model": { "type": "model", "model": "item/loreprelude" }
      },
      {
        "when": "loreprofanedguardians",
        "model": { "type": "model", "model": "item/loreprofanedguardians" }
      },
      {
        "when": "loreprovidence",
        "model": { "type": "model", "model": "item/loreprovidence" }
      },
      {
        "when": "lorequeenbee",
        "model": { "type": "model", "model": "item/lorequeenbee" }
      },
      {
        "when": "lorequeenslime",
        "model": { "type": "model", "model": "item/lorequeenslime" }
      },
      {
        "when": "loreravager",
        "model": { "type": "model", "model": "item/loreravager" }
      },
      {
        "when": "lorerequiem",
        "model": { "type": "model", "model": "item/lorerequiem" }
      },
      {
        "when": "loresignus",
        "model": { "type": "model", "model": "item/loresignus" }
      },
      {
        "when": "loreskeletron",
        "model": { "type": "model", "model": "item/loreskeletron" }
      },
      {
        "when": "loreskeletronprime",
        "model": { "type": "model", "model": "item/loreskeletronprime" }
      },
      {
        "when": "loreslimegod",
        "model": { "type": "model", "model": "item/loreslimegod" }
      },
      {
        "when": "lorestormweaver",
        "model": { "type": "model", "model": "item/lorestormweaver" }
      },
      {
        "when": "loresulphursea",
        "model": { "type": "model", "model": "item/loresulphursea" }
      },
      {
        "when": "loretwins",
        "model": { "type": "model", "model": "item/loretwins" }
      },
      {
        "when": "loreunderworld",
        "model": { "type": "model", "model": "item/loreunderworld" }
      },
      {
        "when": "lorewallofflesh",
        "model": { "type": "model", "model": "item/lorewallofflesh" }
      },
      {
        "when": "loreyharon",
        "model": { "type": "model", "model": "item/loreyharon" }
      },
      {
        "when": "aberrantwritings",
        "model": { "type": "model", "model": "item/aberrantwritings" }
      },
      {
        "when": "absencenotice",
        "model": { "type": "model", "model": "item/absencenotice" }
      },
      {
        "when": "acidicprayerbook",
        "model": { "type": "model", "model": "item/acidicprayerbook" }
      },
      {
        "when": "ancientwritings",
        "model": { "type": "model", "model": "item/ancientwritings" }
      },
      {
        "when": "applethesis",
        "model": { "type": "model", "model": "item/applethesis" }
      },
      {
        "when": "astralinjection",
        "model": { "type": "model", "model": "item/astralinjection" }
      },
      {
        "when": "bestpricebestiary",
        "model": { "type": "model", "model": "item/bestpricebestiary" }
      },
      {
        "when": "bibleofslime",
        "model": { "type": "model", "model": "item/bibleofslime" }
      },
      {
        "when": "bookofmiracles",
        "model": { "type": "model", "model": "item/bookofmiracles" }
      },
      {
        "when": "boundingpotion",
        "model": { "type": "model", "model": "item/boundingpotion" }
      },
      {
        "when": "cactome",
        "model": { "type": "model", "model": "item/cactome" }
      },
      {
        "when": "ceaselesshungerpotion",
        "model": { "type": "model", "model": "item/ceaselesshungerpotion" }
      },
      {
        "when": "clovermanual",
        "model": { "type": "model", "model": "item/clovermanual" }
      },
      {
        "when": "crownjewel",
        "model": { "type": "model", "model": "item/crownjewel" }
      },
      {
        "when": "decayingtome",
        "model": { "type": "model", "model": "item/decayingtome" }
      },
      {
        "when": "dubiousbrochurecorruption",
        "model": { "type": "model", "model": "item/dubiousbrochurecorruption" }
      },
      {
        "when": "dubiousbrochurecrimson",
        "model": { "type": "model", "model": "item/dubiousbrochurecrimson" }
      },
      {
        "when": "dubiousspellbook",
        "model": { "type": "model", "model": "item/dubiousspellbook" }
      },
      {
        "when": "dustydiary",
        "model": { "type": "model", "model": "item/dustydiary" }
      },
      {
        "when": "etherealtalisman",
        "model": { "type": "model", "model": "item/etherealtalisman" }
      },
      {
        "when": "exoblueprints",
        "model": { "type": "model", "model": "item/exoblueprints" }
      },
      {
        "when": "fanaticalramblings",
        "model": { "type": "model", "model": "item/fanaticalramblings" }
      },
      {
        "when": "fishingcatalogue",
        "model": { "type": "model", "model": "item/fishingcatalogue" }
      },
      {
        "when": "flaskofbrimstone",
        "model": { "type": "model", "model": "item/flaskofbrimstone" }
      },
      {
        "when": "flaskofcrumbling",
        "model": { "type": "model", "model": "item/flaskofcrumbling" }
      },
      {
        "when": "frostypamphlet",
        "model": { "type": "model", "model": "item/frostypamphlet" }
      },
      {
        "when": "futuristictreatise",
        "model": { "type": "model", "model": "item/futuristictreatise" }
      },
      {
        "when": "gravitynormalizerpotion",
        "model": { "type": "model", "model": "item/gravitynormalizerpotion" }
      },
      {
        "when": "hitechinstructionmanual",
        "model": { "type": "model", "model": "item/hitechinstructionmanual" }
      },
      {
        "when": "howtofly",
        "model": { "type": "model", "model": "item/howtofly" }
      },
      {
        "when": "inscrutabletexts",
        "model": { "type": "model", "model": "item/inscrutabletexts" }
      },
      {
        "when": "instructionmanual",
        "model": { "type": "model", "model": "item/instructionmanual" }
      },
      {
        "when": "invisibleinkdissertation",
        "model": { "type": "model", "model": "item/invisibleinkdissertation" }
      },
      {
        "when": "lifejelly",
        "model": { "type": "model", "model": "item/lifejelly" }
      },
      {
        "when": "magiclexicon",
        "model": { "type": "model", "model": "item/magiclexicon" }
      },
      {
        "when": "meldconstruct",
        "model": { "type": "model", "model": "item/meldconstruct" }
      },
      {
        "when": "nilkcarton",
        "model": { "type": "model", "model": "item/nilkcarton" }
      },
      {
        "when": "ominousstorybook",
        "model": { "type": "model", "model": "item/ominousstorybook" }
      },
      {
        "when": "otherworldly1",
        "model": { "type": "model", "model": "item/otherworldly1" }
      },
      {
        "when": "otherworldly2",
        "model": { "type": "model", "model": "item/otherworldly2" }
      },
      {
        "when": "otherworldly3",
        "model": { "type": "model", "model": "item/otherworldly3" }
      },
      {
        "when": "otherworldly4",
        "model": { "type": "model", "model": "item/otherworldly4" }
      },
      {
        "when": "otherworldly5",
        "model": { "type": "model", "model": "item/otherworldly5" }
      },
      {
        "when": "otherworldly6",
        "model": { "type": "model", "model": "item/otherworldly6" }
      },
      {
        "when": "pearlshard",
        "model": { "type": "model", "model": "item/pearlshard" }
      },
      {
        "when": "permafrostsconcoction",
        "model": { "type": "model", "model": "item/permafrostsconcoction" }
      },
      {
        "when": "photosynthesispotion",
        "model": { "type": "model", "model": "item/photosynthesispotion" }
      },
      {
        "when": "potionofomniscience",
        "model": { "type": "model", "model": "item/potionofomniscience" }
      },
      {
        "when": "rageofthedeities",
        "model": { "type": "model", "model": "item/rageofthedeities" }
      },
      {
        "when": "sanguinewildlife",
        "model": { "type": "model", "model": "item/sanguinewildlife" }
      },
      {
        "when": "scuttlersjewel",
        "model": { "type": "model", "model": "item/scuttlersjewel" }
      },
      {
        "when": "seamapcollection",
        "model": { "type": "model", "model": "item/seamapcollection" }
      },
      {
        "when": "searemains",
        "model": { "type": "model", "model": "item/searemains" }
      },
      {
        "when": "soaringpotion",
        "model": { "type": "model", "model": "item/soaringpotion" }
      },
      {
        "when": "sulfuricleaflet",
        "model": { "type": "model", "model": "item/sulfuricleaflet" }
      },
      {
        "when": "thebookofshaders",
        "model": { "type": "model", "model": "item/thebookofshaders" }
      },
      {
        "when": "twentytwome",
        "model": { "type": "model", "model": "item/twentytwome" }
      },
      {
        "when": "unfinishedcoloringbook",
        "model": { "type": "model", "model": "item/unfinishedcoloringbook" }
      },
      {
        "when": "vitaljelly",
        "model": { "type": "model", "model": "item/vitaljelly" }
      },
      {
        "when": "wulfrumassemblyguide",
        "model": { "type": "model", "model": "item/wulfrumassemblyguide" }
      },
      {
        "when": "zenpotion",
        "model": { "type": "model", "model": "item/zenpotion" }
      },
      {
        "when": "zergpotion",
        "model": { "type": "model", "model": "item/zergpotion" }
      },
      {
        "when": "aerialhamaxe",
        "model": { "type": "model", "model": "item/aerialhamaxe" }
      },
      {
        "when": "astralpickaxe",
        "model": { "type": "model", "model": "item/astralpickaxe" }
      },
      {
        "when": "axeofpurity",
        "model": { "type": "model", "model": "item/axeofpurity" }
      },
      {
        "when": "beastialpickaxe",
        "model": { "type": "model", "model": "item/beastialpickaxe" }
      },
      {
        "when": "berserkerwaraxe",
        "model": { "type": "model", "model": "item/berserkerwaraxe" }
      },
      {
        "when": "fellerofevergreens",
        "model": { "type": "model", "model": "item/fellerofevergreens" }
      },
      {
        "when": "gelpick",
        "model": { "type": "model", "model": "item/gelpick" }
      },
      {
        "when": "genesispickaxe",
        "model": { "type": "model", "model": "item/genesispickaxe" }
      },
      {
        "when": "infernacutter",
        "model": { "type": "model", "model": "item/infernacutter" }
      },
      {
        "when": "seismichampick",
        "model": { "type": "model", "model": "item/seismichampick" }
      },
      {
        "when": "skyfringepickaxe",
        "model": { "type": "model", "model": "item/skyfringepickaxe" }
      },
      {
        "when": "universesplitter",
        "model": {"type": "model", "model": "item/universesplitter"}
      }
     ]
  }
}